[{"latitude":37.2791863,"longitude":127.0440499,"step":0,"light":320,"activity":"[\"확률 : 100%, 활동 : STILL\",\"확률 : -1%, 활동 : UNKNOWN\"]","time":"2020-07-08 15:38:28.463849"},{"latitude":37.2791863,"longitude":127.0440499,"step":0,"light":320,"activity":"[\"확률 : 100%, 활동 : STILL\",\"확률 : -1%, 활동 : UNKNOWN\"]","time":"2020-07-08 15:38:38.465051"},{"latitude":37.2791863,"longitude":127.0440499,"step":0,"light":320,"activity":"[\"확률 : 100%, 활동 : STILL\",\"확률 : -1%, 활동 : UNKNOWN\"]","time":"2020-07-08 15:38:48.464317"},{"latitude":37.2791863,"longitude":127.0440499,"step":0,"light":320,"activity":"[\"확률 : 100%, 활동 : STILL\",\"확률 : -1%, 활동 : UNKNOWN\"]","time":"2020-07-08 15:38:58.464611"},{"latitude":37.2791863,"longitude":127.0440499,"step":0,"light":320,"activity":"[\"확률 : 100%, 활동 : STILL\",\"확률 : -1%, 활동 : UNKNOWN\"]","time":"2020-07-08 15:39:08.464289"},{"latitude":37.2791863,"longitude":127.0440499,"step":0,"light":320,"activity":"[\"확률 : 100%, 활동 : STILL\",\"확률 : -1%, 활동 : UNKNOWN\"]","time":"2020-07-08 15:39:18.464657"},{"latitude":37.2791863,"longitude":127.0440499,"step":0,"light":320,"activity":"[\"확률 : 100%, 활동 : STILL\",\"확률 : -1%, 활동 : UNKNOWN\"]","time":"2020-07-08 15:39:28.462085"},{"latitude":37.2791863,"longitude":127.0440499,"step":0,"light":320,"activity":"[\"확률 : 100%, 활동 : STILL\",\"확률 : -1%, 활동 : UNKNOWN\"]","time":"2020-07-08 15:39:38.464218"},{"latitude":37.2791863,"longitude":127.0440499,"step":0,"light":320,"activity":"[\"확률 : 100%, 활동 : STILL\",\"확률 : -1%, 활동 : UNKNOWN\"]","time":"2020-07-08 15:39:48.464774"},{"latitude":37.2791863,"longitude":127.0440499,"step":0,"light":320,"activity":"[\"확률 : 100%, 활동 : STILL\",\"확률 : -1%, 활동 : UNKNOWN\"]","time":"2020-07-08 15:39:58.464176"},{"latitude":37.2791863,"longitude":127.0440499,"step":0,"light":320,"activity":"[\"확률 : 100%, 활동 : STILL\",\"확률 : -1%, 활동 : UNKNOWN\"]","time":"2020-07-08 15:40:08.465077"},{"latitude":37.2791863,"longitude":127.0440499,"step":0,"light":320,"activity":"[\"확률 : 100%, 활동 : STILL\",\"확률 : -1%, 활동 : UNKNOWN\"]","time":"2020-07-08 15:40:18.464661"}]