[{"latitude":37.2791863,"longitude":127.0440499,"step":0,"light":320,"activity":"[\"확률 : 100%, 활동 : STILL\",\"확률 : -1%, 활동 : UNKNOWN\"]","time":"2020-07-08 16:35:18.463965"},{"latitude":37.2791863,"longitude":127.0440499,"step":0,"light":320,"activity":"[\"확률 : 100%, 활동 : STILL\",\"확률 : -1%, 활동 : UNKNOWN\"]","time":"2020-07-08 16:35:28.455959"},{"latitude":37.2791863,"longitude":127.0440499,"step":0,"light":320,"activity":"[\"확률 : 100%, 활동 : STILL\",\"확률 : -1%, 활동 : UNKNOWN\"]","time":"2020-07-08 16:35:38.465311"},{"latitude":37.2791863,"longitude":127.0440499,"step":0,"light":320,"activity":"[\"확률 : 100%, 활동 : STILL\",\"확률 : -1%, 활동 : UNKNOWN\"]","time":"2020-07-08 16:35:48.465020"},{"latitude":37.2791863,"longitude":127.0440499,"step":0,"light":320,"activity":"[\"확률 : 100%, 활동 : STILL\",\"확률 : -1%, 활동 : UNKNOWN\"]","time":"2020-07-08 16:35:58.463359"},{"latitude":37.2791863,"longitude":127.0440499,"step":0,"light":320,"activity":"[\"확률 : 40%, 활동 : UNKNOWN\",\"확률 : 10%, 활동 : IN_VEHICLE\",\"확률 : 10%, 활동 : ON_BICYCLE\",\"확률 : 10%, 활동 : ON_FOOT\",\"확률 : 10%, 활동 : WALKING\",\"확률 : 10%, 활동 : RUNNING\",\"확률 : 10%, 활동 : STILL\",\"확률 : 10%, 활동 : UNKNOWN\",\"확률 : 10%, 활동 : UNKNOWN\",\"확률 : 10%, 활동 : UNKNOWN\",\"확률 : 10%, 활동 : UNKNOWN\",\"확률 : 0%, 활동 : UNKNOWN\"]","time":"2020-07-08 16:36:09.141496"},{"latitude":37.2791863,"longitude":127.0440499,"step":0,"light":320,"activity":"[\"확률 : 40%, 활동 : UNKNOWN\",\"확률 : 10%, 활동 : IN_VEHICLE\",\"확률 : 10%, 활동 : ON_BICYCLE\",\"확률 : 10%, 활동 : ON_FOOT\",\"확률 : 10%, 활동 : WALKING\",\"확률 : 10%, 활동 : RUNNING\",\"확률 : 10%, 활동 : STILL\",\"확률 : 10%, 활동 : UNKNOWN\",\"확률 : 10%, 활동 : UNKNOWN\",\"확률 : 10%, 활동 : UNKNOWN\",\"확률 : 10%, 활동 : UNKNOWN\",\"확률 : 0%, 활동 : UNKNOWN\"]","time":"2020-07-08 16:36:47.686262"},{"latitude":37.2791863,"longitude":127.0440499,"step":0,"light":320,"activity":"[\"확률 : 99%, 활동 : STILL\",\"확률 : 1%, 활동 : UNKNOWN\",\"확률 : -1%, 활동 : UNKNOWN\"]","time":"2020-07-08 16:37:01.196998"},{"latitude":37.2791863,"longitude":127.0440499,"step":0,"light":320,"activity":"[\"확률 : 99%, 활동 : STILL\",\"확률 : 1%, 활동 : UNKNOWN\",\"확률 : -1%, 활동 : UNKNOWN\"]","time":"2020-07-08 16:37:16.192401"},{"latitude":37.2791863,"longitude":127.0440499,"step":0,"light":320,"activity":"[\"확률 : 99%, 활동 : STILL\",\"확률 : 1%, 활동 : UNKNOWN\",\"확률 : -1%, 활동 : UNKNOWN\"]","time":"2020-07-08 16:37:26.191699"},{"latitude":37.2791863,"longitude":127.0440499,"step":0,"light":320,"activity":"[\"확률 : 40%, 활동 : UNKNOWN\",\"확률 : 10%, 활동 : IN_VEHICLE\",\"확률 : 10%, 활동 : ON_BICYCLE\",\"확률 : 10%, 활동 : ON_FOOT\",\"확률 : 10%, 활동 : WALKING\",\"확률 : 10%, 활동 : RUNNING\",\"확률 : 10%, 활동 : STILL\",\"확률 : 10%, 활동 : UNKNOWN\",\"확률 : 10%, 활동 : UNKNOWN\",\"확률 : 10%, 활동 : UNKNOWN\",\"확률 : 10%, 활동 : UNKNOWN\",\"확률 : 0%, 활동 : UNKNOWN\"]","time":"2020-07-08 16:37:43.403612"},{"latitude":37.2791863,"longitude":127.0440499,"step":0,"light":320,"activity":"[\"확률 : 40%, 활동 : UNKNOWN\",\"확률 : 10%, 활동 : IN_VEHICLE\",\"확률 : 10%, 활동 : ON_BICYCLE\",\"확률 : 10%, 활동 : ON_FOOT\",\"확률 : 10%, 활동 : WALKING\",\"확률 : 10%, 활동 : RUNNING\",\"확률 : 10%, 활동 : STILL\",\"확률 : 10%, 활동 : UNKNOWN\",\"확률 : 10%, 활동 : UNKNOWN\",\"확률 : 10%, 활동 : UNKNOWN\",\"확률 : 10%, 활동 : UNKNOWN\",\"확률 : 0%, 활동 : UNKNOWN\"]","time":"2020-07-08 16:37:53.414342"},{"latitude":37.2791863,"longitude":127.0440499,"step":0,"light":320,"activity":"[\"확률 : 40%, 활동 : UNKNOWN\",\"확률 : 10%, 활동 : IN_VEHICLE\",\"확률 : 10%, 활동 : ON_BICYCLE\",\"확률 : 10%, 활동 : ON_FOOT\",\"확률 : 10%, 활동 : WALKING\",\"확률 : 10%, 활동 : RUNNING\",\"확률 : 10%, 활동 : STILL\",\"확률 : 10%, 활동 : UNKNOWN\",\"확률 : 10%, 활동 : UNKNOWN\",\"확률 : 10%, 활동 : UNKNOWN\",\"확률 : 10%, 활동 : UNKNOWN\",\"확률 : 0%, 활동 : UNKNOWN\"]","time":"2020-07-08 16:38:04.300315"},{"latitude":37.2791863,"longitude":127.0440499,"step":0,"light":320,"activity":"[\"확률 : 36%, 활동 : STILL\",\"확률 : 27%, 활동 : IN_VEHICLE\",\"확률 : 27%, 활동 : UNKNOWN\",\"확률 : 27%, 활동 : UNKNOWN\",\"확률 : 27%, 활동 : UNKNOWN\",\"확률 : 24%, 활동 : UNKNOWN\",\"확률 : 10%, 활동 : ON_FOOT\",\"확률 : 10%, 활동 : WALKING\",\"확률 : 2%, 활동 : UNKNOWN\",\"확률 : 1%, 활동 : ON_BICYCLE\",\"확률 : -1%, 활동 : UNKNOWN\"]","time":"2020-07-08 16:38:14.291404"},{"latitude":37.2791863,"longitude":127.0440499,"step":0,"light":320,"activity":"[\"확률 : 36%, 활동 : STILL\",\"확률 : 27%, 활동 : IN_VEHICLE\",\"확률 : 27%, 활동 : UNKNOWN\",\"확률 : 27%, 활동 : UNKNOWN\",\"확률 : 27%, 활동 : UNKNOWN\",\"확률 : 24%, 활동 : UNKNOWN\",\"확률 : 10%, 활동 : ON_FOOT\",\"확률 : 10%, 활동 : WALKING\",\"확률 : 2%, 활동 : UNKNOWN\",\"확률 : 1%, 활동 : ON_BICYCLE\",\"확률 : -1%, 활동 : UNKNOWN\"]","time":"2020-07-08 16:39:10.385086"},{"latitude":37.2791863,"longitude":127.0440499,"step":0,"light":320,"activity":"[\"확률 : 40%, 활동 : UNKNOWN\",\"확률 : 10%, 활동 : IN_VEHICLE\",\"확률 : 10%, 활동 : ON_BICYCLE\",\"확률 : 10%, 활동 : ON_FOOT\",\"확률 : 10%, 활동 : WALKING\",\"확률 : 10%, 활동 : RUNNING\",\"확률 : 10%, 활동 : STILL\",\"확률 : 10%, 활동 : UNKNOWN\",\"확률 : 10%, 활동 : UNKNOWN\",\"확률 : 10%, 활동 : UNKNOWN\",\"확률 : 10%, 활동 : UNKNOWN\",\"확률 : 0%, 활동 : UNKNOWN\"]","time":"2020-07-08 16:39:20.325776"},{"latitude":37.2791863,"longitude":127.0440499,"step":0,"light":320,"activity":"[\"확률 : 40%, 활동 : UNKNOWN\",\"확률 : 10%, 활동 : IN_VEHICLE\",\"확률 : 10%, 활동 : ON_BICYCLE\",\"확률 : 10%, 활동 : ON_FOOT\",\"확률 : 10%, 활동 : WALKING\",\"확률 : 10%, 활동 : RUNNING\",\"확률 : 10%, 활동 : STILL\",\"확률 : 10%, 활동 : UNKNOWN\",\"확률 : 10%, 활동 : UNKNOWN\",\"확률 : 10%, 활동 : UNKNOWN\",\"확률 : 10%, 활동 : UNKNOWN\",\"확률 : 0%, 활동 : UNKNOWN\"]","time":"2020-07-08 16:39:30.332265"},{"latitude":37.2791863,"longitude":127.0440499,"step":0,"light":320,"activity":"[\"확률 : 40%, 활동 : UNKNOWN\",\"확률 : 10%, 활동 : IN_VEHICLE\",\"확률 : 10%, 활동 : ON_BICYCLE\",\"확률 : 10%, 활동 : ON_FOOT\",\"확률 : 10%, 활동 : WALKING\",\"확률 : 10%, 활동 : RUNNING\",\"확률 : 10%, 활동 : STILL\",\"확률 : 10%, 활동 : UNKNOWN\",\"확률 : 10%, 활동 : UNKNOWN\",\"확률 : 10%, 활동 : UNKNOWN\",\"확률 : 10%, 활동 : UNKNOWN\",\"확률 : 0%, 활동 : UNKNOWN\"]","time":"2020-07-08 16:39:40.331322"},{"latitude":37.2791863,"longitude":127.0440499,"step":0,"light":320,"activity":"[\"확률 : 40%, 활동 : UNKNOWN\",\"확률 : 10%, 활동 : IN_VEHICLE\",\"확률 : 10%, 활동 : ON_BICYCLE\",\"확률 : 10%, 활동 : ON_FOOT\",\"확률 : 10%, 활동 : WALKING\",\"확률 : 10%, 활동 : RUNNING\",\"확률 : 10%, 활동 : STILL\",\"확률 : 10%, 활동 : UNKNOWN\",\"확률 : 10%, 활동 : UNKNOWN\",\"확률 : 10%, 활동 : UNKNOWN\",\"확률 : 10%, 활동 : UNKNOWN\",\"확률 : 0%, 활동 : UNKNOWN\"]","time":"2020-07-08 16:39:50.332509"},{"latitude":37.2791863,"longitude":127.0440499,"step":0,"light":320,"activity":"[\"확률 : 39%, 활동 : STILL\",\"확률 : 35%, 활동 : ON_FOOT\",\"확률 : 35%, 활동 : WALKING\",\"확률 : 11%, 활동 : ON_BICYCLE\",\"확률 : 7%, 활동 : IN_VEHICLE\",\"확률 : 7%, 활동 : UNKNOWN\",\"확률 : 5%, 활동 : UNKNOWN\",\"확률 : 5%, 활동 : UNKNOWN\",\"확률 : 5%, 활동 : UNKNOWN\",\"확률 : 2%, 활동 : UNKNOWN\",\"확률 : 1%, 활동 : RUNNING\",\"확률 : -1%, 활동 : UNKNOWN\"]","time":"2020-07-08 16:40:00.332245"},{"latitude":37.2791863,"longitude":127.0440499,"step":0,"light":320,"activity":"[\"확률 : 39%, 활동 : STILL\",\"확률 : 35%, 활동 : ON_FOOT\",\"확률 : 35%, 활동 : WALKING\",\"확률 : 11%, 활동 : ON_BICYCLE\",\"확률 : 7%, 활동 : IN_VEHICLE\",\"확률 : 7%, 활동 : UNKNOWN\",\"확률 : 5%, 활동 : UNKNOWN\",\"확률 : 5%, 활동 : UNKNOWN\",\"확률 : 5%, 활동 : UNKNOWN\",\"확률 : 2%, 활동 : UNKNOWN\",\"확률 : 1%, 활동 : RUNNING\",\"확률 : -1%, 활동 : UNKNOWN\"]","time":"2020-07-08 16:40:10.331165"}]